torznab/__init__.py
torznab/core.py
torznab/exceptions.py
torznab/parser.py
torznab/types.py
torznab/validators.py
torznab-0.0.2.dist-info/METADATA
torznab-0.0.2.dist-info/WHEEL
torznab-0.0.2.dist-info/licenses/LICENSE
torznab-0.0.2.dist-info/RECORD
