Metadata-Version: 2.4
Name: torznab
Version: 0.0.2
Summary: python implementation for torznab api
Project-URL: Homepage, https://github.com/miikaoskari/torznab
Author: miikaoskari
License: MIT License
License-File: LICENSE
Keywords: torrent,torznab
Classifier: Development Status :: 3 - Alpha
Classifier: Intended Audience :: Developers
Classifier: License :: OSI Approved :: MIT License
Classifier: Programming Language :: Python :: 3.13
Requires-Python: >=3.9
Requires-Dist: requests
